inmanta_plugins/aws/__init__.py
inmanta_plugins/aws/setup.cfg
inmanta_plugins/aws/model/_init.cf
inmanta_plugins/aws/model/analytics.cf
inmanta_plugins/aws/model/database.cf
inmanta_plugins/aws/model/os.cf
inmanta_module_aws-4.0.6.dist-info/METADATA
inmanta_module_aws-4.0.6.dist-info/WHEEL
inmanta_module_aws-4.0.6.dist-info/top_level.txt
inmanta_module_aws-4.0.6.dist-info/RECORD
