Metadata-Version: 2.1
Name: inmanta-module-aws
Version: 4.0.6
License: Apache 2.0
Requires-Dist: inmanta-module-ssh
Requires-Dist: inmanta-module-std
Requires-Dist: boto3<2,>=1.26
